CHANGES.rst
LICENSE.txt
MANIFEST.in
README.rst
setup.py
src/attribute_wrapper/__init__.py
src/attribute_wrapper/attribute_wrapper.py
src/attribute_wrapper.egg-info/PKG-INFO
src/attribute_wrapper.egg-info/SOURCES.txt
src/attribute_wrapper.egg-info/dependency_links.txt
src/attribute_wrapper.egg-info/requires.txt
src/attribute_wrapper.egg-info/top_level.txt
src/attribute_wrapper.egg-info/zip-safe