Metadata-Version: 1.1
Name: attribute-wrapper
Version: 0.1.2
Summary: Class wrapper, which maps attribute calls to HTTP API.
Home-page: https://github.com/Bystroushaak/attribute_wrapper
Author: Bystroushaak
Author-email: bystrousak@kitakitsune.org
License: MIT
Platform: UNKNOWN
Classifier: Topic :: Utilities
Classifier: Topic :: Internet :: WWW/HTTP
Classifier: Programming Language :: Python :: 2.7
Classifier: License :: OSI Approved :: MIT License
Classifier: Topic :: Software Development :: Libraries
